{
  "totalRides": 42437,
  "totalIncidents": 15975,
  "totalKm": 344781,
  "diffDate": "01.05.2021, 23:00:06",
  "regions": [
    {
      "name": "Berlin",
      "rides": [
        20765,
        2
      ],
      "incidents": [
        9068,
        3
      ],
      "scaryIncidents": [
        2285,
        1
      ],
      "km": [
        172632,
        10
      ]
    },
    {
      "name": "UNKNOWN",
      "rides": [
        5036,
        75
      ],
      "incidents": [
        2289,
        16
      ],
      "scaryIncidents": [
        323,
        2
      ],
      "km": [
        45437,
        612
      ]
    },
    {
      "name": "other",
      "rides": [
        2992,
        52
      ],
      "incidents": [
        680,
        23
      ],
      "scaryIncidents": [
        102,
        5
      ],
      "km": [
        26937,
        567
      ]
    },
    {
      "name": "Wuppertal",
      "rides": [
        2140,
        4
      ],
      "incidents": [
        228,
        0
      ],
      "scaryIncidents": [
        39,
        0
      ],
      "km": [
        15836,
        62
      ]
    },
    {
      "name": "Hannover",
      "rides": [
        2048,
        3
      ],
      "incidents": [
        879,
        5
      ],
      "scaryIncidents": [
        123,
        1
      ],
      "km": [
        14516,
        76
      ]
    },
    {
      "name": "Ruhrgebiet",
      "rides": [
        1880,
        1
      ],
      "incidents": [
        622,
        0
      ],
      "scaryIncidents": [
        187,
        0
      ],
      "km": [
        13953,
        10
      ]
    },
    {
      "name": "Bern",
      "rides": [
        1443,
        8
      ],
      "incidents": [
        119,
        0
      ],
      "scaryIncidents": [
        29,
        0
      ],
      "km": [
        10770,
        42
      ]
    },
    {
      "name": "Eichwalde",
      "rides": [
        936,
        3
      ],
      "incidents": [
        54,
        0
      ],
      "scaryIncidents": [
        7,
        0
      ],
      "km": [
        8573,
        34
      ]
    },
    {
      "name": "Augsburg",
      "rides": [
        901,
        5
      ],
      "incidents": [
        164,
        0
      ],
      "scaryIncidents": [
        31,
        0
      ],
      "km": [
        6015,
        100
      ]
    },
    {
      "name": "München",
      "rides": [
        598,
        3
      ],
      "incidents": [
        269,
        11
      ],
      "scaryIncidents": [
        28,
        0
      ],
      "km": [
        4219,
        24
      ]
    },
    {
      "name": "Stuttgart",
      "rides": [
        504,
        2
      ],
      "incidents": [
        444,
        1
      ],
      "scaryIncidents": [
        42,
        0
      ],
      "km": [
        5558,
        15
      ]
    },
    {
      "name": "Konstanz",
      "rides": [
        431,
        29
      ],
      "incidents": [
        94,
        5
      ],
      "scaryIncidents": [
        27,
        2
      ],
      "km": [
        2757,
        202
      ]
    },
    {
      "name": "Leipzig",
      "rides": [
        340,
        2
      ],
      "incidents": [
        102,
        0
      ],
      "scaryIncidents": [
        10,
        0
      ],
      "km": [
        1498,
        11
      ]
    },
    {
      "name": "Nuernberg",
      "rides": [
        286,
        10
      ],
      "incidents": [
        304,
        0
      ],
      "scaryIncidents": [
        57,
        0
      ],
      "km": [
        2172,
        116
      ]
    },
    {
      "name": "Bielefeld",
      "rides": [
        262,
        12
      ],
      "incidents": [
        25,
        0
      ],
      "scaryIncidents": [
        5,
        0
      ],
      "km": [
        1656,
        21
      ]
    },
    {
      "name": "Pforzheim",
      "rides": [
        257,
        8
      ],
      "incidents": [
        71,
        0
      ],
      "scaryIncidents": [
        24,
        0
      ],
      "km": [
        1226,
        26
      ]
    },
    {
      "name": "Düsseldorf",
      "rides": [
        188,
        1
      ],
      "incidents": [
        44,
        0
      ],
      "scaryIncidents": [
        10,
        0
      ],
      "km": [
        1969,
        4
      ]
    },
    {
      "name": "Karlsruhe",
      "rides": [
        185,
        4
      ],
      "incidents": [
        89,
        2
      ],
      "scaryIncidents": [
        26,
        0
      ],
      "km": [
        1231,
        23
      ]
    },
    {
      "name": "ZES_Experimentell",
      "rides": [
        174,
        0
      ],
      "incidents": [
        52,
        0
      ],
      "scaryIncidents": [
        5,
        0
      ],
      "km": [
        719,
        0
      ]
    },
    {
      "name": "Mannheim",
      "rides": [
        148,
        16
      ],
      "incidents": [
        25,
        0
      ],
      "scaryIncidents": [
        5,
        0
      ],
      "km": [
        641,
        66
      ]
    },
    {
      "name": "Dresden",
      "rides": [
        136,
        3
      ],
      "incidents": [
        38,
        0
      ],
      "scaryIncidents": [
        6,
        0
      ],
      "km": [
        984,
        21
      ]
    },
    {
      "name": "Freiburg",
      "rides": [
        115,
        9
      ],
      "incidents": [
        47,
        2
      ],
      "scaryIncidents": [
        7,
        2
      ],
      "km": [
        627,
        62
      ]
    },
    {
      "name": "Mainz",
      "rides": [
        77,
        9
      ],
      "incidents": [
        80,
        23
      ],
      "scaryIncidents": [
        21,
        0
      ],
      "km": [
        576,
        24
      ]
    },
    {
      "name": "Rastatt",
      "rides": [
        70,
        1
      ],
      "incidents": [
        27,
        0
      ],
      "scaryIncidents": [
        3,
        0
      ],
      "km": [
        721,
        21
      ]
    },
    {
      "name": "Tübingen",
      "rides": [
        56,
        2
      ],
      "incidents": [
        15,
        2
      ],
      "scaryIncidents": [
        3,
        0
      ],
      "km": [
        354,
        20
      ]
    },
    {
      "name": "Landau",
      "rides": [
        51,
        1
      ],
      "incidents": [
        21,
        0
      ],
      "scaryIncidents": [
        3,
        0
      ],
      "km": [
        509,
        3
      ]
    },
    {
      "name": "Bruchsal",
      "rides": [
        50,
        34
      ],
      "incidents": [
        18,
        7
      ],
      "scaryIncidents": [
        0,
        0
      ],
      "km": [
        283,
        204
      ]
    },
    {
      "name": "Breisgau-Hochschwarzwald",
      "rides": [
        42,
        20
      ],
      "incidents": [
        7,
        0
      ],
      "scaryIncidents": [
        3,
        0
      ],
      "km": [
        213,
        132
      ]
    },
    {
      "name": "Frankfurt",
      "rides": [
        38,
        1
      ],
      "incidents": [
        11,
        0
      ],
      "scaryIncidents": [
        2,
        0
      ],
      "km": [
        158,
        17
      ]
    },
    {
      "name": "Koblenz",
      "rides": [
        34,
        0
      ],
      "incidents": [
        9,
        0
      ],
      "scaryIncidents": [
        4,
        0
      ],
      "km": [
        100,
        0
      ]
    },
    {
      "name": "Alzey",
      "rides": [
        30,
        0
      ],
      "incidents": [
        7,
        0
      ],
      "scaryIncidents": [
        2,
        0
      ],
      "km": [
        59,
        0
      ]
    },
    {
      "name": "Saarlouis",
      "rides": [
        28,
        3
      ],
      "incidents": [
        7,
        0
      ],
      "scaryIncidents": [
        2,
        0
      ],
      "km": [
        227,
        20
      ]
    },
    {
      "name": "Odenwald",
      "rides": [
        27,
        15
      ],
      "incidents": [
        27,
        8
      ],
      "scaryIncidents": [
        5,
        1
      ],
      "km": [
        295,
        203
      ]
    },
    {
      "name": "Kaiserslautern",
      "rides": [
        22,
        2
      ],
      "incidents": [
        1,
        0
      ],
      "scaryIncidents": [
        1,
        0
      ],
      "km": [
        68,
        3
      ]
    },
    {
      "name": "Ortenau",
      "rides": [
        21,
        11
      ],
      "incidents": [
        4,
        0
      ],
      "scaryIncidents": [
        0,
        0
      ],
      "km": [
        100,
        21
      ]
    },
    {
      "name": "Weimar",
      "rides": [
        18,
        2
      ],
      "incidents": [
        2,
        0
      ],
      "scaryIncidents": [
        0,
        0
      ],
      "km": [
        70,
        3
      ]
    },
    {
      "name": "Sigmaringen",
      "rides": [
        8,
        0
      ],
      "incidents": [
        0,
        0
      ],
      "scaryIncidents": [
        0,
        0
      ],
      "km": [
        70,
        0
      ]
    },
    {
      "name": "Ulm",
      "rides": [
        8,
        0
      ],
      "incidents": [
        4,
        0
      ],
      "scaryIncidents": [
        1,
        0
      ],
      "km": [
        62,
        0
      ]
    },
    {
      "name": "Calw",
      "rides": [
        8,
        0
      ],
      "incidents": [
        0,
        0
      ],
      "scaryIncidents": [
        0,
        0
      ],
      "km": [
        184,
        0
      ]
    },
    {
      "name": "Trier",
      "rides": [
        8,
        0
      ],
      "incidents": [
        15,
        0
      ],
      "scaryIncidents": [
        2,
        0
      ],
      "km": [
        78,
        0
      ]
    },
    {
      "name": "Bruehl",
      "rides": [
        8,
        0
      ],
      "incidents": [
        2,
        0
      ],
      "scaryIncidents": [
        0,
        0
      ],
      "km": [
        43,
        0
      ]
    },
    {
      "name": "Vulkaneifel",
      "rides": [
        7,
        0
      ],
      "incidents": [
        2,
        0
      ],
      "scaryIncidents": [
        0,
        0
      ],
      "km": [
        50,
        0
      ]
    },
    {
      "name": "Aschaffenburg",
      "rides": [
        7,
        2
      ],
      "incidents": [
        0,
        0
      ],
      "scaryIncidents": [
        0,
        0
      ],
      "km": [
        44,
        5
      ]
    },
    {
      "name": "Tuttlingen",
      "rides": [
        6,
        1
      ],
      "incidents": [
        1,
        0
      ],
      "scaryIncidents": [
        0,
        0
      ],
      "km": [
        54,
        9
      ]
    },
    {
      "name": "Ostalbkreis",
      "rides": [
        5,
        0
      ],
      "incidents": [
        1,
        0
      ],
      "scaryIncidents": [
        0,
        0
      ],
      "km": [
        54,
        0
      ]
    },
    {
      "name": "Bad-Kreuznach",
      "rides": [
        5,
        0
      ],
      "incidents": [
        0,
        0
      ],
      "scaryIncidents": [
        0,
        0
      ],
      "km": [
        29,
        0
      ]
    },
    {
      "name": "Ahrweiler",
      "rides": [
        5,
        0
      ],
      "incidents": [
        1,
        0
      ],
      "scaryIncidents": [
        0,
        0
      ],
      "km": [
        68,
        0
      ]
    },
    {
      "name": "Wetterau",
      "rides": [
        4,
        0
      ],
      "incidents": [
        1,
        0
      ],
      "scaryIncidents": [
        0,
        0
      ],
      "km": [
        55,
        0
      ]
    },
    {
      "name": "Emmendingen",
      "rides": [
        3,
        0
      ],
      "incidents": [
        4,
        0
      ],
      "scaryIncidents": [
        1,
        0
      ],
      "km": [
        29,
        0
      ]
    },
    {
      "name": "Heilbronn",
      "rides": [
        3,
        0
      ],
      "incidents": [
        1,
        0
      ],
      "scaryIncidents": [
        0,
        0
      ],
      "km": [
        13,
        0
      ]
    },
    {
      "name": "Lörrach",
      "rides": [
        3,
        1
      ],
      "incidents": [
        0,
        0
      ],
      "scaryIncidents": [
        0,
        0
      ],
      "km": [
        30,
        10
      ]
    },
    {
      "name": "Saarbrücken",
      "rides": [
        2,
        0
      ],
      "incidents": [
        0,
        0
      ],
      "scaryIncidents": [
        0,
        0
      ],
      "km": [
        26,
        0
      ]
    },
    {
      "name": "Reutlingen",
      "rides": [
        2,
        0
      ],
      "incidents": [
        0,
        0
      ],
      "scaryIncidents": [
        0,
        0
      ],
      "km": [
        7,
        0
      ]
    },
    {
      "name": "Neckar-Odenwald",
      "rides": [
        2,
        0
      ],
      "incidents": [
        0,
        0
      ],
      "scaryIncidents": [
        0,
        0
      ],
      "km": [
        29,
        0
      ]
    },
    {
      "name": "Rottweil",
      "rides": [
        2,
        0
      ],
      "incidents": [
        0,
        0
      ],
      "scaryIncidents": [
        0,
        0
      ],
      "km": [
        39,
        0
      ]
    },
    {
      "name": "Friedrichshafen",
      "rides": [
        2,
        0
      ],
      "incidents": [
        0,
        0
      ],
      "scaryIncidents": [
        0,
        0
      ],
      "km": [
        80,
        0
      ]
    },
    {
      "name": "Saarpfalz",
      "rides": [
        2,
        0
      ],
      "incidents": [
        0,
        0
      ],
      "scaryIncidents": [
        0,
        0
      ],
      "km": [
        4,
        0
      ]
    },
    {
      "name": "Fulda",
      "rides": [
        2,
        0
      ],
      "incidents": [
        0,
        0
      ],
      "scaryIncidents": [
        0,
        0
      ],
      "km": [
        20,
        0
      ]
    },
    {
      "name": "Heidenheim",
      "rides": [
        1,
        0
      ],
      "incidents": [
        0,
        0
      ],
      "scaryIncidents": [
        0,
        0
      ],
      "km": [
        20,
        0
      ]
    },
    {
      "name": "Darmstadt",
      "rides": [
        1,
        0
      ],
      "incidents": [
        0,
        0
      ],
      "scaryIncidents": [
        0,
        0
      ],
      "km": [
        4,
        0
      ]
    },
    {
      "name": "Gießen",
      "rides": [
        1,
        0
      ],
      "incidents": [
        0,
        0
      ],
      "scaryIncidents": [
        0,
        0
      ],
      "km": [
        13,
        0
      ]
    },
    {
      "name": "Westerwald",
      "rides": [
        1,
        0
      ],
      "incidents": [
        0,
        0
      ],
      "scaryIncidents": [
        0,
        0
      ],
      "km": [
        2,
        0
      ]
    },
    {
      "name": "Taunus",
      "rides": [
        1,
        0
      ],
      "incidents": [
        0,
        0
      ],
      "scaryIncidents": [
        0,
        0
      ],
      "km": [
        15,
        0
      ]
    },
    {
      "name": "Neuwied",
      "rides": [
        1,
        0
      ],
      "incidents": [
        0,
        0
      ],
      "scaryIncidents": [
        0,
        0
      ],
      "km": [
        0,
        0
      ]
    }
  ],
  "sourceDate": "02.05.2021, 23:00:06"
}