{
  "totalRides": 53072,
  "totalIncidents": 20487,
  "totalKm": 426575,
  "diffDate": "29.07.2021, 23:00:07",
  "regions": [
    {
      "name": "Berlin",
      "rides": [
        22924,
        153
      ],
      "incidents": [
        10404,
        183
      ],
      "scaryIncidents": [
        2711,
        74
      ],
      "km": [
        186591,
        1052
      ]
    },
    {
      "name": "UNKNOWN",
      "rides": [
        5134,
        2
      ],
      "incidents": [
        2318,
        2
      ],
      "scaryIncidents": [
        331,
        0
      ],
      "km": [
        46288,
        26
      ]
    },
    {
      "name": "other",
      "rides": [
        3521,
        28
      ],
      "incidents": [
        830,
        16
      ],
      "scaryIncidents": [
        151,
        5
      ],
      "km": [
        31677,
        302
      ]
    },
    {
      "name": "Hannover",
      "rides": [
        2942,
        369
      ],
      "incidents": [
        1268,
        27
      ],
      "scaryIncidents": [
        195,
        5
      ],
      "km": [
        24784,
        4171
      ]
    },
    {
      "name": "Wuppertal",
      "rides": [
        2325,
        10
      ],
      "incidents": [
        255,
        1
      ],
      "scaryIncidents": [
        50,
        1
      ],
      "km": [
        17917,
        152
      ]
    },
    {
      "name": "Ruhrgebiet",
      "rides": [
        2192,
        9
      ],
      "incidents": [
        778,
        4
      ],
      "scaryIncidents": [
        273,
        4
      ],
      "km": [
        17248,
        125
      ]
    },
    {
      "name": "Bern",
      "rides": [
        2170,
        0
      ],
      "incidents": [
        122,
        0
      ],
      "scaryIncidents": [
        29,
        0
      ],
      "km": [
        13019,
        0
      ]
    },
    {
      "name": "Nuernberg",
      "rides": [
        1770,
        139
      ],
      "incidents": [
        1582,
        174
      ],
      "scaryIncidents": [
        313,
        42
      ],
      "km": [
        13156,
        1006
      ]
    },
    {
      "name": "Eichwalde",
      "rides": [
        1087,
        12
      ],
      "incidents": [
        56,
        0
      ],
      "scaryIncidents": [
        8,
        0
      ],
      "km": [
        10711,
        167
      ]
    },
    {
      "name": "München",
      "rides": [
        1073,
        20
      ],
      "incidents": [
        407,
        2
      ],
      "scaryIncidents": [
        49,
        1
      ],
      "km": [
        8163,
        136
      ]
    },
    {
      "name": "Augsburg",
      "rides": [
        975,
        4
      ],
      "incidents": [
        164,
        0
      ],
      "scaryIncidents": [
        31,
        0
      ],
      "km": [
        6405,
        22
      ]
    },
    {
      "name": "Stuttgart",
      "rides": [
        950,
        18
      ],
      "incidents": [
        602,
        5
      ],
      "scaryIncidents": [
        59,
        1
      ],
      "km": [
        11778,
        201
      ]
    },
    {
      "name": "Bielefeld",
      "rides": [
        619,
        62
      ],
      "incidents": [
        44,
        2
      ],
      "scaryIncidents": [
        5,
        0
      ],
      "km": [
        2528,
        135
      ]
    },
    {
      "name": "Konstanz",
      "rides": [
        602,
        2
      ],
      "incidents": [
        124,
        0
      ],
      "scaryIncidents": [
        37,
        0
      ],
      "km": [
        4044,
        4
      ]
    },
    {
      "name": "Mannheim",
      "rides": [
        537,
        20
      ],
      "incidents": [
        106,
        4
      ],
      "scaryIncidents": [
        29,
        2
      ],
      "km": [
        3371,
        57
      ]
    },
    {
      "name": "Dresden",
      "rides": [
        490,
        1
      ],
      "incidents": [
        158,
        0
      ],
      "scaryIncidents": [
        31,
        0
      ],
      "km": [
        4356,
        5
      ]
    },
    {
      "name": "Karlsruhe",
      "rides": [
        485,
        23
      ],
      "incidents": [
        253,
        28
      ],
      "scaryIncidents": [
        58,
        1
      ],
      "km": [
        3628,
        183
      ]
    },
    {
      "name": "Freiburg",
      "rides": [
        402,
        24
      ],
      "incidents": [
        62,
        0
      ],
      "scaryIncidents": [
        11,
        0
      ],
      "km": [
        2057,
        71
      ]
    },
    {
      "name": "Leipzig",
      "rides": [
        399,
        0
      ],
      "incidents": [
        139,
        0
      ],
      "scaryIncidents": [
        12,
        0
      ],
      "km": [
        1815,
        0
      ]
    },
    {
      "name": "Düsseldorf",
      "rides": [
        304,
        1
      ],
      "incidents": [
        46,
        0
      ],
      "scaryIncidents": [
        11,
        0
      ],
      "km": [
        2857,
        3
      ]
    },
    {
      "name": "Pforzheim",
      "rides": [
        263,
        0
      ],
      "incidents": [
        73,
        0
      ],
      "scaryIncidents": [
        24,
        0
      ],
      "km": [
        1251,
        0
      ]
    },
    {
      "name": "ZES_Experimentell",
      "rides": [
        218,
        1
      ],
      "incidents": [
        56,
        0
      ],
      "scaryIncidents": [
        7,
        0
      ],
      "km": [
        848,
        2
      ]
    },
    {
      "name": "Wetterau",
      "rides": [
        179,
        11
      ],
      "incidents": [
        55,
        14
      ],
      "scaryIncidents": [
        7,
        2
      ],
      "km": [
        1925,
        63
      ]
    },
    {
      "name": "Kaiserslautern",
      "rides": [
        172,
        0
      ],
      "incidents": [
        36,
        0
      ],
      "scaryIncidents": [
        11,
        0
      ],
      "km": [
        437,
        0
      ]
    },
    {
      "name": "Saarlouis",
      "rides": [
        131,
        7
      ],
      "incidents": [
        24,
        0
      ],
      "scaryIncidents": [
        7,
        0
      ],
      "km": [
        1084,
        15
      ]
    },
    {
      "name": "Frankfurt",
      "rides": [
        121,
        11
      ],
      "incidents": [
        106,
        21
      ],
      "scaryIncidents": [
        23,
        2
      ],
      "km": [
        646,
        39
      ]
    },
    {
      "name": "Tübingen",
      "rides": [
        108,
        0
      ],
      "incidents": [
        25,
        0
      ],
      "scaryIncidents": [
        7,
        0
      ],
      "km": [
        667,
        0
      ]
    },
    {
      "name": "Mainz",
      "rides": [
        80,
        0
      ],
      "incidents": [
        86,
        0
      ],
      "scaryIncidents": [
        21,
        0
      ],
      "km": [
        585,
        0
      ]
    },
    {
      "name": "Rastatt",
      "rides": [
        80,
        0
      ],
      "incidents": [
        28,
        0
      ],
      "scaryIncidents": [
        3,
        0
      ],
      "km": [
        811,
        0
      ]
    },
    {
      "name": "Tuttlingen",
      "rides": [
        72,
        1
      ],
      "incidents": [
        1,
        0
      ],
      "scaryIncidents": [
        0,
        0
      ],
      "km": [
        212,
        2
      ]
    },
    {
      "name": "Weimar",
      "rides": [
        66,
        0
      ],
      "incidents": [
        20,
        0
      ],
      "scaryIncidents": [
        3,
        0
      ],
      "km": [
        312,
        0
      ]
    },
    {
      "name": "Saarbrücken",
      "rides": [
        66,
        0
      ],
      "incidents": [
        11,
        0
      ],
      "scaryIncidents": [
        9,
        0
      ],
      "km": [
        587,
        0
      ]
    },
    {
      "name": "Koblenz",
      "rides": [
        64,
        16
      ],
      "incidents": [
        17,
        3
      ],
      "scaryIncidents": [
        5,
        0
      ],
      "km": [
        148,
        18
      ]
    },
    {
      "name": "Bruchsal",
      "rides": [
        62,
        0
      ],
      "incidents": [
        20,
        0
      ],
      "scaryIncidents": [
        0,
        0
      ],
      "km": [
        539,
        0
      ]
    },
    {
      "name": "Landau",
      "rides": [
        59,
        0
      ],
      "incidents": [
        21,
        0
      ],
      "scaryIncidents": [
        3,
        0
      ],
      "km": [
        575,
        0
      ]
    },
    {
      "name": "Alzey",
      "rides": [
        58,
        0
      ],
      "incidents": [
        17,
        0
      ],
      "scaryIncidents": [
        4,
        0
      ],
      "km": [
        92,
        0
      ]
    },
    {
      "name": "Ortenau",
      "rides": [
        52,
        5
      ],
      "incidents": [
        5,
        0
      ],
      "scaryIncidents": [
        0,
        0
      ],
      "km": [
        462,
        90
      ]
    },
    {
      "name": "Breisgau-Hochschwarzwald",
      "rides": [
        48,
        0
      ],
      "incidents": [
        9,
        0
      ],
      "scaryIncidents": [
        4,
        0
      ],
      "km": [
        254,
        0
      ]
    },
    {
      "name": "Vulkaneifel",
      "rides": [
        39,
        0
      ],
      "incidents": [
        8,
        0
      ],
      "scaryIncidents": [
        1,
        0
      ],
      "km": [
        245,
        0
      ]
    },
    {
      "name": "Odenwald",
      "rides": [
        31,
        0
      ],
      "incidents": [
        27,
        0
      ],
      "scaryIncidents": [
        5,
        0
      ],
      "km": [
        396,
        0
      ]
    },
    {
      "name": "Darmstadt",
      "rides": [
        29,
        1
      ],
      "incidents": [
        52,
        1
      ],
      "scaryIncidents": [
        11,
        1
      ],
      "km": [
        233,
        2
      ]
    },
    {
      "name": "Trier",
      "rides": [
        19,
        0
      ],
      "incidents": [
        19,
        0
      ],
      "scaryIncidents": [
        2,
        0
      ],
      "km": [
        120,
        0
      ]
    },
    {
      "name": "Bruehl",
      "rides": [
        19,
        0
      ],
      "incidents": [
        11,
        0
      ],
      "scaryIncidents": [
        3,
        0
      ],
      "km": [
        88,
        0
      ]
    },
    {
      "name": "Ulm",
      "rides": [
        14,
        0
      ],
      "incidents": [
        4,
        0
      ],
      "scaryIncidents": [
        1,
        0
      ],
      "km": [
        80,
        0
      ]
    },
    {
      "name": "Sigmaringen",
      "rides": [
        11,
        0
      ],
      "incidents": [
        2,
        0
      ],
      "scaryIncidents": [
        1,
        0
      ],
      "km": [
        81,
        0
      ]
    },
    {
      "name": "Aschaffenburg",
      "rides": [
        10,
        0
      ],
      "incidents": [
        2,
        0
      ],
      "scaryIncidents": [
        0,
        0
      ],
      "km": [
        52,
        0
      ]
    },
    {
      "name": "Calw",
      "rides": [
        9,
        0
      ],
      "incidents": [
        0,
        0
      ],
      "scaryIncidents": [
        0,
        0
      ],
      "km": [
        191,
        0
      ]
    },
    {
      "name": "Taunus",
      "rides": [
        9,
        0
      ],
      "incidents": [
        0,
        0
      ],
      "scaryIncidents": [
        0,
        0
      ],
      "km": [
        373,
        0
      ]
    },
    {
      "name": "Fulda",
      "rides": [
        8,
        0
      ],
      "incidents": [
        0,
        0
      ],
      "scaryIncidents": [
        0,
        0
      ],
      "km": [
        60,
        0
      ]
    },
    {
      "name": "Main-Kinzig",
      "rides": [
        7,
        0
      ],
      "incidents": [
        0,
        0
      ],
      "scaryIncidents": [
        0,
        0
      ],
      "km": [
        119,
        0
      ]
    },
    {
      "name": "Baar",
      "rides": [
        7,
        0
      ],
      "incidents": [
        5,
        0
      ],
      "scaryIncidents": [
        0,
        0
      ],
      "km": [
        29,
        0
      ]
    },
    {
      "name": "Emmendingen",
      "rides": [
        6,
        0
      ],
      "incidents": [
        26,
        0
      ],
      "scaryIncidents": [
        1,
        0
      ],
      "km": [
        119,
        0
      ]
    },
    {
      "name": "Ostalbkreis",
      "rides": [
        5,
        0
      ],
      "incidents": [
        1,
        0
      ],
      "scaryIncidents": [
        0,
        0
      ],
      "km": [
        54,
        0
      ]
    },
    {
      "name": "Bad-Kreuznach",
      "rides": [
        5,
        0
      ],
      "incidents": [
        0,
        0
      ],
      "scaryIncidents": [
        0,
        0
      ],
      "km": [
        29,
        0
      ]
    },
    {
      "name": "Heilbronn",
      "rides": [
        5,
        0
      ],
      "incidents": [
        1,
        0
      ],
      "scaryIncidents": [
        0,
        0
      ],
      "km": [
        15,
        0
      ]
    },
    {
      "name": "Ahrweiler",
      "rides": [
        5,
        0
      ],
      "incidents": [
        1,
        0
      ],
      "scaryIncidents": [
        0,
        0
      ],
      "km": [
        68,
        0
      ]
    },
    {
      "name": "Cochem-Zell",
      "rides": [
        4,
        0
      ],
      "incidents": [
        0,
        0
      ],
      "scaryIncidents": [
        0,
        0
      ],
      "km": [
        28,
        0
      ]
    },
    {
      "name": "Lörrach",
      "rides": [
        3,
        0
      ],
      "incidents": [
        0,
        0
      ],
      "scaryIncidents": [
        0,
        0
      ],
      "km": [
        30,
        0
      ]
    },
    {
      "name": "Biberach",
      "rides": [
        3,
        0
      ],
      "incidents": [
        0,
        0
      ],
      "scaryIncidents": [
        0,
        0
      ],
      "km": [
        42,
        0
      ]
    },
    {
      "name": "Neckar-Odenwald",
      "rides": [
        3,
        0
      ],
      "incidents": [
        0,
        0
      ],
      "scaryIncidents": [
        0,
        0
      ],
      "km": [
        53,
        0
      ]
    },
    {
      "name": "Zollernalbkreis",
      "rides": [
        3,
        0
      ],
      "incidents": [
        0,
        0
      ],
      "scaryIncidents": [
        0,
        0
      ],
      "km": [
        24,
        0
      ]
    },
    {
      "name": "Altenkirchen",
      "rides": [
        2,
        0
      ],
      "incidents": [
        0,
        0
      ],
      "scaryIncidents": [
        0,
        0
      ],
      "km": [
        19,
        0
      ]
    },
    {
      "name": "Reutlingen",
      "rides": [
        2,
        0
      ],
      "incidents": [
        0,
        0
      ],
      "scaryIncidents": [
        0,
        0
      ],
      "km": [
        7,
        0
      ]
    },
    {
      "name": "Rottweil",
      "rides": [
        2,
        0
      ],
      "incidents": [
        0,
        0
      ],
      "scaryIncidents": [
        0,
        0
      ],
      "km": [
        39,
        0
      ]
    },
    {
      "name": "Friedrichshafen",
      "rides": [
        2,
        0
      ],
      "incidents": [
        0,
        0
      ],
      "scaryIncidents": [
        0,
        0
      ],
      "km": [
        80,
        0
      ]
    },
    {
      "name": "Saarpfalz",
      "rides": [
        2,
        0
      ],
      "incidents": [
        0,
        0
      ],
      "scaryIncidents": [
        0,
        0
      ],
      "km": [
        4,
        0
      ]
    },
    {
      "name": "Waldshut",
      "rides": [
        2,
        0
      ],
      "incidents": [
        0,
        0
      ],
      "scaryIncidents": [
        0,
        0
      ],
      "km": [
        7,
        0
      ]
    },
    {
      "name": "Neuwied",
      "rides": [
        1,
        0
      ],
      "incidents": [
        0,
        0
      ],
      "scaryIncidents": [
        0,
        0
      ],
      "km": [
        0,
        0
      ]
    },
    {
      "name": "Heidenheim",
      "rides": [
        1,
        0
      ],
      "incidents": [
        0,
        0
      ],
      "scaryIncidents": [
        0,
        0
      ],
      "km": [
        20,
        0
      ]
    },
    {
      "name": "Memmingen",
      "rides": [
        1,
        0
      ],
      "incidents": [
        0,
        0
      ],
      "scaryIncidents": [
        0,
        0
      ],
      "km": [
        20,
        0
      ]
    },
    {
      "name": "Zweibrücken",
      "rides": [
        1,
        0
      ],
      "incidents": [
        0,
        0
      ],
      "scaryIncidents": [
        0,
        0
      ],
      "km": [
        7,
        0
      ]
    },
    {
      "name": "Gießen",
      "rides": [
        1,
        0
      ],
      "incidents": [
        0,
        0
      ],
      "scaryIncidents": [
        0,
        0
      ],
      "km": [
        13,
        0
      ]
    },
    {
      "name": "Westerwald",
      "rides": [
        1,
        0
      ],
      "incidents": [
        0,
        0
      ],
      "scaryIncidents": [
        0,
        0
      ],
      "km": [
        2,
        0
      ]
    }
  ],
  "sourceDate": "05.08.2021, 23:00:05"
}